<?xml version="1.0" encoding="UTF-8"?>
<!DOCTYPE mapper PUBLIC "-//mybatis.org//DTD Mapper 3.0//EN" "http://mybatis.org/dtd/mybatis-3-mapper.dtd">
<mapper namespace="com.foodie.mapper.ItemsParamDao">

    <resultMap id="BaseResultMap" type="com.foodie.pojo.ItemsParam">
        <!--@Table items_param-->
        <result property="id" column="id" jdbcType="VARCHAR"/>
        <result property="itemId" column="item_id" jdbcType="VARCHAR"/>
        <result property="producPlace" column="produc_place" jdbcType="VARCHAR"/>
        <result property="footPeriod" column="foot_period" jdbcType="VARCHAR"/>
        <result property="brand" column="brand" jdbcType="VARCHAR"/>
        <result property="factoryName" column="factory_name" jdbcType="VARCHAR"/>
        <result property="factoryAddress" column="factory_address" jdbcType="VARCHAR"/>
        <result property="packagingMethod" column="packaging_method" jdbcType="VARCHAR"/>
        <result property="weight" column="weight" jdbcType="VARCHAR"/>
        <result property="storageMethod" column="storage_method" jdbcType="VARCHAR"/>
        <result property="eatMethod" column="eat_method" jdbcType="VARCHAR"/>
        <result property="createdTime" column="created_time" jdbcType="TIMESTAMP"/>
        <result property="updatedTime" column="updated_time" jdbcType="TIMESTAMP"/>
    </resultMap>

    <!--查询单个-->
    <select id="queryById" resultMap="BaseResultMap">
        select
          id, item_id, produc_place, foot_period, brand, factory_name, factory_address, packaging_method, weight, storage_method, eat_method, created_time, updated_time
        from  items_param
        where id = #{id}
    </select>

    <!--查询指定行数据-->
    <select id="queryAllByLimit" resultMap="BaseResultMap">
        select
          id, item_id, produc_place, foot_period, brand, factory_name, factory_address, packaging_method, weight, storage_method, eat_method, created_time, updated_time
        from  items_param
        limit #{offset}, #{limit}
    </select>

    <!--通过实体作为筛选条件查询-->
    <select id="queryAll" resultMap="BaseResultMap">
        select
          id, item_id, produc_place, foot_period, brand, factory_name, factory_address, packaging_method, weight, storage_method, eat_method, created_time, updated_time
        from  items_param
        <where>
            <if test="id != null and id != ''">
                and id = #{id}
            </if>
            <if test="itemId != null and itemId != ''">
                and item_id = #{itemId}
            </if>
            <if test="producPlace != null and producPlace != ''">
                and produc_place = #{producPlace}
            </if>
            <if test="footPeriod != null and footPeriod != ''">
                and foot_period = #{footPeriod}
            </if>
            <if test="brand != null and brand != ''">
                and brand = #{brand}
            </if>
            <if test="factoryName != null and factoryName != ''">
                and factory_name = #{factoryName}
            </if>
            <if test="factoryAddress != null and factoryAddress != ''">
                and factory_address = #{factoryAddress}
            </if>
            <if test="packagingMethod != null and packagingMethod != ''">
                and packaging_method = #{packagingMethod}
            </if>
            <if test="weight != null and weight != ''">
                and weight = #{weight}
            </if>
            <if test="storageMethod != null and storageMethod != ''">
                and storage_method = #{storageMethod}
            </if>
            <if test="eatMethod != null and eatMethod != ''">
                and eat_method = #{eatMethod}
            </if>
            <if test="createdTime != null">
                and created_time = #{createdTime}
            </if>
            <if test="updatedTime != null">
                and updated_time = #{updatedTime}
            </if>
        </where>
    </select>

    <!--新增所有列-->
    <insert id="insert" keyProperty="id" useGeneratedKeys="true">
        insert into  items_param(item_id, produc_place, foot_period, brand, factory_name, factory_address, packaging_method, weight, storage_method, eat_method, created_time, updated_time)
        values (#{itemId}, #{producPlace}, #{footPeriod}, #{brand}, #{factoryName}, #{factoryAddress}, #{packagingMethod}, #{weight}, #{storageMethod}, #{eatMethod}, #{createdTime}, #{updatedTime})
    </insert>

    <!--通过主键修改数据-->
    <update id="update">
        update  items_param
        <set>
            <if test="itemId != null and itemId != ''">
                item_id = #{itemId},
            </if>
            <if test="producPlace != null and producPlace != ''">
                produc_place = #{producPlace},
            </if>
            <if test="footPeriod != null and footPeriod != ''">
                foot_period = #{footPeriod},
            </if>
            <if test="brand != null and brand != ''">
                brand = #{brand},
            </if>
            <if test="factoryName != null and factoryName != ''">
                factory_name = #{factoryName},
            </if>
            <if test="factoryAddress != null and factoryAddress != ''">
                factory_address = #{factoryAddress},
            </if>
            <if test="packagingMethod != null and packagingMethod != ''">
                packaging_method = #{packagingMethod},
            </if>
            <if test="weight != null and weight != ''">
                weight = #{weight},
            </if>
            <if test="storageMethod != null and storageMethod != ''">
                storage_method = #{storageMethod},
            </if>
            <if test="eatMethod != null and eatMethod != ''">
                eat_method = #{eatMethod},
            </if>
            <if test="createdTime != null">
                created_time = #{createdTime},
            </if>
            <if test="updatedTime != null">
                updated_time = #{updatedTime},
            </if>
        </set>
        where id = #{id}
    </update>

    <!--通过主键删除-->
    <delete id="deleteById">
        delete from  items_param where id = #{id}
    </delete>

</mapper>